exploitfarm/__init__.py
exploitfarm/__main__.py
exploitfarm/_init_exposed.py
exploitfarm/xfarm.py
exploitfarm/xploit.py
exploitfarm/models/__init__.py
exploitfarm/models/client.py
exploitfarm/models/dbtypes.py
exploitfarm/models/enums.py
exploitfarm/models/exploit.py
exploitfarm/models/flags.py
exploitfarm/models/groups.py
exploitfarm/models/response.py
exploitfarm/models/service.py
exploitfarm/models/submitter.py
exploitfarm/models/teams.py
exploitfarm/tui/__init__.py
exploitfarm/tui/config.py
exploitfarm/tui/exploitdownload.py
exploitfarm/tui/exploitinit.py
exploitfarm/tui/group_prejoin.py
exploitfarm/tui/group_select.py
exploitfarm/tui/login.py
exploitfarm/tui/shared_attack_group.py
exploitfarm/tui/startxploit.py
exploitfarm/utils/__init__.py
exploitfarm/utils/cmd.py
exploitfarm/utils/config.py
exploitfarm/utils/exploit.py
exploitfarm/utils/reqs.py
exploitfarm/utils/windows_close_fix.py
exploitfarm-1.2.12.data/scripts/xfarm
exploitfarm-1.2.12.dist-info/METADATA
exploitfarm-1.2.12.dist-info/WHEEL
exploitfarm-1.2.12.dist-info/top_level.txt
exploitfarm-1.2.12.dist-info/RECORD
