Metadata-Version: 2.4
Name: exploitfarm
Version: 1.2.12
Summary: Exploit Farm client
Home-page: https://github.com/pwnzer0tt1/exploitfarm
Author: Pwnzer0tt1
Author-email: pwnzer0tt1@poliba.it
Classifier: Programming Language :: Python :: 3
Classifier: License :: OSI Approved :: GNU General Public License v3 or later (GPLv3+)
Classifier: Operating System :: OS Independent
Requires-Python: >=3.10
Requires-Dist: requests>=2.32.3
Requires-Dist: urllib3>=2.5.0
Requires-Dist: python-dateutil==2.9.0.post0
Requires-Dist: pydantic>=2
Requires-Dist: typing-extensions>=4.7.1
Requires-Dist: fasteners==0.19
Requires-Dist: toml==0.10.2
Requires-Dist: psutil==7.0.0
Requires-Dist: dirhash==0.5.0
Requires-Dist: requests-toolbelt==1.0.0
Requires-Dist: python-socketio[client]==5.14.1
Requires-Dist: textual>=3.0.0
Requires-Dist: typer>=0.16
Requires-Dist: xfarm
Requires-Dist: orjson
Dynamic: author
Dynamic: author-email
Dynamic: classifier
Dynamic: description
Dynamic: description-content-type
Dynamic: home-page
Dynamic: requires-dist
Dynamic: requires-python
Dynamic: summary
